{
  "project_info": {
    "project_number": "585168952312",
    "project_id": "pucara-323413",
    "storage_bucket": "pucara-323413.appspot.com"
  },
  "client": [
    {
      "client_info": {
        "mobilesdk_app_id": "1:585168952312:android:38d6944e5fa6b22a45940d",
        "android_client_info": {
          "package_name": "com.pucara"
        }
      },
      "oauth_client": [
        {
          "client_id": "585168952312-5og5up5on92gipqkj7ri8kbgdtgql3bg.apps.googleusercontent.com",
          "client_type": 1,
          "android_info": {
            "package_name": "com.pucara",
            "certificate_hash": "5e8f16062ea3cd2c4a0d547876baa6f38cabf625"
          }
        },
        {
          "client_id": "585168952312-21ifrioqeq688jfl6unshgrdjoafl8hb.apps.googleusercontent.com",
          "client_type": 3
        }
      ],
      "api_key": [
        {
          "current_key": "AIzaSyD_FHtGfQrkHXFVjAldUn2Qo5KYyPdxN_Y"
        }
      ],
      "services": {
        "appinvite_service": {
          "other_platform_oauth_client": [
            {
              "client_id": "585168952312-21ifrioqeq688jfl6unshgrdjoafl8hb.apps.googleusercontent.com",
              "client_type": 3
            }
          ]
        }
      }
    }
  ],
  "configuration_version": "1"
}